bridgestyle/__init__.py
bridgestyle/style2style.py
bridgestyle/version.py
bridgestyle/arcgis/__init__.py
bridgestyle/arcgis/constants.py
bridgestyle/arcgis/expressions.py
bridgestyle/arcgis/fromgeostyler.py
bridgestyle/arcgis/togeostyler.py
bridgestyle/arcgis/wkt_geometries.py
bridgestyle/geostyler/__init__.py
bridgestyle/geostyler/custom_properties.py
bridgestyle/mapboxgl/__init__.py
bridgestyle/mapboxgl/fromgeostyler.py
bridgestyle/mapboxgl/togeostyler.py
bridgestyle/mapserver/__init__.py
bridgestyle/mapserver/fromgeostyler.py
bridgestyle/mapserver/togeostyler.py
bridgestyle/qgis/__init__.py
bridgestyle/qgis/expressions.py
bridgestyle/qgis/fromgeostyler.py
bridgestyle/qgis/togeostyler.py
bridgestyle/sld/__init__.py
bridgestyle/sld/fromgeostyler.py
bridgestyle/sld/parsecdata.py
bridgestyle/sld/togeostyler.py
bridgestyle/sld/transformations.py
bridgestyle-0.1.5.dist-info/licenses/LICENSE.md
bridgestyle-0.1.5.dist-info/METADATA
bridgestyle-0.1.5.dist-info/WHEEL
bridgestyle-0.1.5.dist-info/entry_points.txt
bridgestyle-0.1.5.dist-info/top_level.txt
bridgestyle-0.1.5.dist-info/RECORD
