Metadata-Version: 2.4
Name: bridgestyle
Version: 0.1.5
Summary: A Python library to convert between different map style formats
Author-email: GeoCat BV <bridge@geocat.net>
License-Expression: MIT
Project-URL: Repository, https://github.com/GeoCat/bridge-style
Keywords: GeoCat,Bridge,style,symbology,styling,mapping,SLD,cartography,Mapfile,CIM,GeoStyler,Mapbox,QGIS,GeoServer,Esri
Classifier: Development Status :: 4 - Beta
Classifier: Intended Audience :: Developers
Classifier: Programming Language :: Python :: 3
Classifier: Programming Language :: Python :: 3.9
Classifier: Programming Language :: Python :: 3.10
Classifier: Programming Language :: Python :: 3.11
Classifier: Programming Language :: Python :: 3.12
Classifier: Topic :: Scientific/Engineering :: GIS
Requires-Python: >=3.9
License-File: LICENSE.md
Dynamic: license-file
